pysuperfab/__init__.py
pysuperfab/juliapkg.json
pysuperfab-0.5.16.dist-info/licenses/LICENSE
pysuperfab-0.5.16.dist-info/METADATA
pysuperfab-0.5.16.dist-info/WHEEL
pysuperfab-0.5.16.dist-info/top_level.txt
pysuperfab-0.5.16.dist-info/RECORD
