Metadata-Version: 2.4
Name: pysuperfab
Version: 0.5.16
Summary: Python wrapper for SphericalFourierBesselDecompositions.jl
Author-email: Henry Gebhardt <gebhardt@caltech.edu>
License-Expression: Apache-2.0
Project-URL: Homepage, https://github.com/hsgg/SphericalFourierBesselDecompositions.jl
Project-URL: Repository, https://github.com/hsgg/SphericalFourierBesselDecompositions.jl
License-File: LICENSE
Requires-Dist: juliacall
Dynamic: license-file
